portfolio/__init__.py
portfolio/portfolio_report.py
portfolio/setup.py
f_teixeira_portfolio-0.0.1.dist-info/LICENSE
f_teixeira_portfolio-0.0.1.dist-info/METADATA
f_teixeira_portfolio-0.0.1.dist-info/WHEEL
f_teixeira_portfolio-0.0.1.dist-info/top_level.txt
f_teixeira_portfolio-0.0.1.dist-info/RECORD
