Metadata-Version: 2.1
Name: f-teixeira-portfolio
Version: 0.0.1
Summary: an IEX stock report generator
Author-email: Frank Teixeira <franciscokix@yahoo.ca>
Project-URL: Homepage, https://github.com/sheridan-python/assignment-7-portfolio-generator-franciscokix
Classifier: Programming Language :: Python :: 3
Classifier: License :: OSI Approved :: MIT License
Classifier: Operating System :: OS Independent
Requires-Python: >=3.7
License-File: LICENSE
